hi.py
pneumoultramicroscopicossilicovulcanoconiose-0.0.1.dist-info/METADATA
pneumoultramicroscopicossilicovulcanoconiose-0.0.1.dist-info/WHEEL
pneumoultramicroscopicossilicovulcanoconiose-0.0.1.dist-info/top_level.txt
pneumoultramicroscopicossilicovulcanoconiose-0.0.1.dist-info/RECORD
