Metadata-Version: 2.4
Name: pneumoultramicroscopicossilicovulcanoconiose
Version: 0.0.1
Summary: Extremely advanced alphabet printing technology
Author: Murilo
